{"modelName": "devise-220528-v0-ep33", "version": "1", "fileId": "0cd3beb23228476783295c93a200cb0f", "classIds": ["Crex crex", "Scolopax rusticola"], "channels": [[{"startTime": 0.0, "endTime": 5.0, "predictions": {"probabilities": [-12.210981369018555, -12.716534614562988], "logits": [NaN, NaN]}, "groundTruth": [0.0, 0.0]}, {"startTime": 5.0, "endTime": 10.0, "predictions": {"probabilities": [-10.585345268249512, -12.92844009399414], "logits": [NaN, NaN]}, "groundTruth": [0.0, 0.0]}, {"startTime": 10.0, "endTime": 15.0, "predictions": {"probabilities": [-15.758742332458496, -17.35417366027832], "logits": [NaN, NaN]}, "groundTruth": [0.0, 0.0]}, {"startTime": 15.0, "endTime": 20.0, "predictions": {"probabilities": [-14.962038040161133, -12.165308952331543], "logits": [NaN, NaN]}, "groundTruth": [0.0, 0.0]}]]}