{"modelName": "devise-220528-v0-ep33", "version": "1", "fileId": "1ba28cb8d1cd4bfea008adc7882cfc4b", "classIds": ["Crex crex", "Scolopax rusticola"], "channels": [[{"startTime": 0.0, "endTime": 5.0, "predictions": {"probabilities": [-15.12614917755127, -18.975093841552734], "logits": [NaN, NaN]}, "groundTruth": [0.0, 0.0]}, {"startTime": 5.0, "endTime": 10.0, "predictions": {"probabilities": [-8.841418266296387, -7.391213893890381], "logits": [NaN, NaN]}, "groundTruth": [0.0, 0.0]}, {"startTime": 10.0, "endTime": 15.0, "predictions": {"probabilities": [-11.50833797454834, -14.12973690032959], "logits": [NaN, NaN]}, "groundTruth": [0.0, 0.0]}, {"startTime": 15.0, "endTime": 20.0, "predictions": {"probabilities": [-12.630975723266602, -9.335338592529297], "logits": [NaN, NaN]}, "groundTruth": [0.0, 0.0]}]]}