{"modelName": "devise-220528-v0-ep33", "version": "1", "fileId": "1c56fa41fdb44611a7c475a43f0927d3", "classIds": ["Crex crex", "Scolopax rusticola"], "channels": [[{"startTime": 0.0, "endTime": 5.0, "predictions": {"probabilities": [-11.040932655334473, -8.560914993286133], "logits": [NaN, NaN]}, "groundTruth": [0.0, 0.0]}, {"startTime": 5.0, "endTime": 10.0, "predictions": {"probabilities": [-11.271474838256836, -12.961176872253418], "logits": [NaN, NaN]}, "groundTruth": [0.0, 0.0]}, {"startTime": 10.0, "endTime": 15.0, "predictions": {"probabilities": [-9.929608345031738, -11.141618728637695], "logits": [NaN, NaN]}, "groundTruth": [0.0, 0.0]}, {"startTime": 15.0, "endTime": 20.0, "predictions": {"probabilities": [-10.483108520507812, -10.89498233795166], "logits": [NaN, NaN]}, "groundTruth": [0.0, 0.0]}]]}