{"modelName": "devise-220528-v0-ep33", "version": "1", "fileId": "2b71b57dc128426c845cae5d86b4b1ed", "classIds": ["Crex crex", "Scolopax rusticola"], "channels": [[{"startTime": 0.0, "endTime": 5.0, "predictions": {"probabilities": [4.1104634362909565e-08, 4.178394519271933e-09], "logits": []}, "groundTruth": [0.0, 0.0]}, {"startTime": 5.0, "endTime": 10.0, "predictions": {"probabilities": [6.102848004729822e-08, 1.2731721232839277e-09], "logits": []}, "groundTruth": [0.0, 0.0]}, {"startTime": 10.0, "endTime": 15.0, "predictions": {"probabilities": [1.3821214395193238e-08, 1.6082704612507825e-10], "logits": []}, "groundTruth": [0.0, 0.0]}, {"startTime": 15.0, "endTime": 20.0, "predictions": {"probabilities": [2.514546849852195e-06, 2.8164104151073843e-06], "logits": []}, "groundTruth": [0.0, 0.0]}]]}