{"modelName": "devise-220528-v0-ep33", "version": "1", "fileId": "346911b18fa745c496d4a9878a225b4e", "classIds": ["Crex crex", "Scolopax rusticola"], "channels": [[{"startTime": 0.0, "endTime": 5.0, "predictions": {"probabilities": [9.945756028173491e-05, 2.2524362066178583e-05], "logits": []}, "groundTruth": [0.0, 0.0]}, {"startTime": 5.0, "endTime": 10.0, "predictions": {"probabilities": [2.3131938178266864e-06, 1.8752490671403166e-09], "logits": []}, "groundTruth": [0.0, 0.0]}, {"startTime": 10.0, "endTime": 15.0, "predictions": {"probabilities": [9.815142402658239e-05, 7.067695264595386e-07], "logits": []}, "groundTruth": [0.0, 0.0]}, {"startTime": 15.0, "endTime": 20.0, "predictions": {"probabilities": [0.005415479186922312, 4.2611518438206986e-06], "logits": []}, "groundTruth": [0.0, 0.0]}]]}