{"modelName": "devise-220528-v0-ep33", "version": "1", "fileId": "3fc0e8848b114411a34d52bd3a02e319", "classIds": ["Crex crex", "Scolopax rusticola"], "channels": [[{"startTime": 0.0, "endTime": 5.0, "predictions": {"probabilities": [-11.067182540893555, -10.325333595275879], "logits": [NaN, NaN]}, "groundTruth": [0.0, 0.0]}, {"startTime": 5.0, "endTime": 10.0, "predictions": {"probabilities": [-12.53834342956543, -10.765212059020996], "logits": [NaN, NaN]}, "groundTruth": [0.0, 0.0]}, {"startTime": 10.0, "endTime": 15.0, "predictions": {"probabilities": [-13.149672508239746, -8.359697341918945], "logits": [NaN, NaN]}, "groundTruth": [0.0, 0.0]}, {"startTime": 15.0, "endTime": 20.0, "predictions": {"probabilities": [-11.43401050567627, -10.638466835021973], "logits": [NaN, NaN]}, "groundTruth": [0.0, 0.0]}]]}