{"modelName": "devise-220528-v0-ep33", "version": "1", "fileId": "4a56e5636af74b52887b6cb9a0f77a06", "classIds": ["Crex crex", "Scolopax rusticola"], "channels": [[{"startTime": 0.0, "endTime": 5.0, "predictions": {"probabilities": [5.954304924671305e-07, 3.373001788986585e-07], "logits": []}, "groundTruth": [0.0, 0.0]}, {"startTime": 5.0, "endTime": 10.0, "predictions": {"probabilities": [1.8904782336903736e-05, 1.3254918485472444e-05], "logits": []}, "groundTruth": [0.0, 0.0]}, {"startTime": 10.0, "endTime": 15.0, "predictions": {"probabilities": [2.332074700461817e-06, 1.0478717058504117e-06], "logits": []}, "groundTruth": [0.0, 0.0]}, {"startTime": 15.0, "endTime": 20.0, "predictions": {"probabilities": [3.9477576763147226e-08, 1.8191638417874856e-08], "logits": []}, "groundTruth": [0.0, 0.0]}]]}