{"modelName": "devise-220528-v0-ep33", "version": "1", "fileId": "60273cd155ae4e55a2d29818abf8c35e", "classIds": ["Crex crex", "Scolopax rusticola"], "channels": [[{"startTime": 0.0, "endTime": 5.0, "predictions": {"probabilities": [-13.312294006347656, -11.950235366821289], "logits": [NaN, NaN]}, "groundTruth": [0.0, 0.0]}, {"startTime": 5.0, "endTime": 10.0, "predictions": {"probabilities": [-15.308300971984863, -15.841374397277832], "logits": [NaN, NaN]}, "groundTruth": [0.0, 0.0]}, {"startTime": 10.0, "endTime": 15.0, "predictions": {"probabilities": [-14.758024215698242, -10.79308032989502], "logits": [NaN, NaN]}, "groundTruth": [0.0, 0.0]}, {"startTime": 15.0, "endTime": 20.0, "predictions": {"probabilities": [-14.127556800842285, -7.634908676147461], "logits": [NaN, NaN]}, "groundTruth": [0.0, 0.0]}]]}