{"modelName": "devise-220528-v0-ep33", "version": "1", "fileId": "ae7e4f176dc64cb69d565add0537f31a", "classIds": ["Crex crex", "Scolopax rusticola"], "channels": [[{"startTime": 0.0, "endTime": 5.0, "predictions": {"probabilities": [-10.50611686706543, 3.849428653717041], "logits": [NaN, NaN]}, "groundTruth": [0.0, 1.0]}, {"startTime": 5.0, "endTime": 10.0, "predictions": {"probabilities": [-16.075227737426758, 14.088546752929688], "logits": [NaN, NaN]}, "groundTruth": [0.0, 1.0]}, {"startTime": 10.0, "endTime": 15.0, "predictions": {"probabilities": [-10.425200462341309, -2.5089659690856934], "logits": [NaN, NaN]}, "groundTruth": [0.0, 1.0]}, {"startTime": 13.0, "endTime": 18.0, "predictions": {"probabilities": [-7.422642707824707, -7.353906154632568], "logits": [NaN, NaN]}, "groundTruth": [0.0, 1.0]}]]}