{"modelName": "devise-220528-v0-ep33", "version": "1", "fileId": "b1f14deb19bd4e0a963cb30c3297a734", "classIds": ["Crex crex", "Scolopax rusticola"], "channels": [[{"startTime": 0.0, "endTime": 5.0, "predictions": {"probabilities": [-16.603395462036133, 8.738715171813965], "logits": [NaN, NaN]}, "groundTruth": [0.0, 1.0]}, {"startTime": 5.0, "endTime": 10.0, "predictions": {"probabilities": [-19.93964385986328, 7.164620399475098], "logits": [NaN, NaN]}, "groundTruth": [0.0, 1.0]}, {"startTime": 10.0, "endTime": 15.0, "predictions": {"probabilities": [-16.122222900390625, -4.033132553100586], "logits": [NaN, NaN]}, "groundTruth": [0.0, 1.0]}, {"startTime": 15.0, "endTime": 20.0, "predictions": {"probabilities": [-18.073894500732422, 2.212332010269165], "logits": [NaN, NaN]}, "groundTruth": [0.0, 1.0]}, {"startTime": 20.0, "endTime": 25.0, "predictions": {"probabilities": [-15.23206901550293, 9.72232437133789], "logits": [NaN, NaN]}, "groundTruth": [0.0, 1.0]}, {"startTime": 25.0, "endTime": 30.0, "predictions": {"probabilities": [-13.716192245483398, 2.0477333068847656], "logits": [NaN, NaN]}, "groundTruth": [0.0, 1.0]}, {"startTime": 26.0, "endTime": 31.0, "predictions": {"probabilities": [-15.38261604309082, 0.05166710168123245], "logits": [NaN, -2.909884214401245]}, "groundTruth": [0.0, 1.0]}]]}