{"modelName": "devise-220528-v0-ep33", "version": "1", "fileId": "b8d4a58f823d458caf565f4476a3221a", "classIds": ["Crex crex", "Scolopax rusticola"], "channels": [[{"startTime": 0.0, "endTime": 5.0, "predictions": {"probabilities": [-12.246938705444336, -15.59927749633789], "logits": [NaN, NaN]}, "groundTruth": [0.0, 0.0]}, {"startTime": 5.0, "endTime": 10.0, "predictions": {"probabilities": [-15.638656616210938, -25.919376373291016], "logits": [NaN, NaN]}, "groundTruth": [0.0, 0.0]}, {"startTime": 10.0, "endTime": 15.0, "predictions": {"probabilities": [-13.680901527404785, -15.646931648254395], "logits": [NaN, NaN]}, "groundTruth": [0.0, 0.0]}, {"startTime": 15.0, "endTime": 20.0, "predictions": {"probabilities": [-14.762455940246582, -16.385488510131836], "logits": [NaN, NaN]}, "groundTruth": [0.0, 0.0]}]]}