{"modelName": "devise-220528-v0-ep33", "version": "1", "fileId": "c506e6128df34782b92807de718275d6", "classIds": ["Crex crex", "Scolopax rusticola"], "channels": [[{"startTime": 0.0, "endTime": 5.0, "predictions": {"probabilities": [-15.309796333312988, -16.681358337402344], "logits": [NaN, NaN]}, "groundTruth": [0.0, 0.0]}, {"startTime": 5.0, "endTime": 10.0, "predictions": {"probabilities": [-18.39382553100586, -18.822065353393555], "logits": [NaN, NaN]}, "groundTruth": [0.0, 0.0]}, {"startTime": 10.0, "endTime": 15.0, "predictions": {"probabilities": [-12.798800468444824, -12.417476654052734], "logits": [NaN, NaN]}, "groundTruth": [0.0, 0.0]}, {"startTime": 15.0, "endTime": 20.0, "predictions": {"probabilities": [-11.852861404418945, -25.010910034179688], "logits": [NaN, NaN]}, "groundTruth": [0.0, 0.0]}]]}