{"modelName": "devise-220528-v0-ep33", "version": "1", "fileId": "c902a61864a34786bd55496f33e7e34d", "classIds": ["Crex crex", "Scolopax rusticola"], "channels": [[{"startTime": 0.0, "endTime": 5.0, "predictions": {"probabilities": [-11.033905982971191, -9.179373741149902], "logits": [NaN, NaN]}, "groundTruth": [0.0, 0.0]}, {"startTime": 5.0, "endTime": 10.0, "predictions": {"probabilities": [-14.322275161743164, -14.635802268981934], "logits": [NaN, NaN]}, "groundTruth": [0.0, 0.0]}, {"startTime": 10.0, "endTime": 15.0, "predictions": {"probabilities": [-9.941231727600098, -13.10538387298584], "logits": [NaN, NaN]}, "groundTruth": [0.0, 0.0]}, {"startTime": 15.0, "endTime": 20.0, "predictions": {"probabilities": [-12.643414497375488, -14.64859676361084], "logits": [NaN, NaN]}, "groundTruth": [0.0, 0.0]}]]}