{"modelName": "devise-220528-v0-ep33", "version": "1", "fileId": "ddaba2ae3e6a42f4af55fa606be68a3c", "classIds": ["Crex crex", "Scolopax rusticola"], "channels": [[{"startTime": 0.0, "endTime": 5.0, "predictions": {"probabilities": [-16.65006446838379, -4.7900471687316895], "logits": [NaN, NaN]}, "groundTruth": [0.0, 1.0]}, {"startTime": 5.0, "endTime": 10.0, "predictions": {"probabilities": [-15.5890531539917, -12.067319869995117], "logits": [NaN, NaN]}, "groundTruth": [0.0, 1.0]}, {"startTime": 10.0, "endTime": 15.0, "predictions": {"probabilities": [-17.08452033996582, 27.654083251953125], "logits": [NaN, NaN]}, "groundTruth": [0.0, 1.0]}, {"startTime": 15.0, "endTime": 20.0, "predictions": {"probabilities": [-21.082059860229492, 23.726282119750977], "logits": [NaN, NaN]}, "groundTruth": [0.0, 1.0]}, {"startTime": 19.0, "endTime": 24.0, "predictions": {"probabilities": [-17.038286209106445, 16.545520782470703], "logits": [NaN, NaN]}, "groundTruth": [0.0, 0.0]}]]}