{"modelName": "devise-220528-v0-ep33", "version": "1", "fileId": "f749da30cc1d44c9a082cc61e917cb4f", "classIds": ["Crex crex", "Scolopax rusticola"], "channels": [[{"startTime": 0.0, "endTime": 5.0, "predictions": {"probabilities": [3.2697537335479865e-06, 7.590512041133479e-08], "logits": []}, "groundTruth": [0.0, 0.0]}, {"startTime": 5.0, "endTime": 10.0, "predictions": {"probabilities": [1.588996155987843e-06, 3.836909399979049e-06], "logits": []}, "groundTruth": [0.0, 0.0]}, {"startTime": 10.0, "endTime": 15.0, "predictions": {"probabilities": [2.8871983886347152e-05, 3.332424114432797e-07], "logits": []}, "groundTruth": [0.0, 0.0]}, {"startTime": 15.0, "endTime": 20.0, "predictions": {"probabilities": [1.5855501800388083e-08, 5.378902323549539e-10], "logits": []}, "groundTruth": [0.0, 0.0]}]]}