{"modelName": "devise-220528-v0-ep33", "version": "1", "fileId": "fedf293d297d4d988461e11f8ab6e4cc", "classIds": ["Crex crex", "Scolopax rusticola"], "channels": [[{"startTime": 0.0, "endTime": 5.0, "predictions": {"probabilities": [-12.06944751739502, -12.784366607666016], "logits": [NaN, NaN]}, "groundTruth": [0.0, 0.0]}, {"startTime": 5.0, "endTime": 10.0, "predictions": {"probabilities": [-12.655479431152344, -11.524317741394043], "logits": [NaN, NaN]}, "groundTruth": [0.0, 0.0]}, {"startTime": 10.0, "endTime": 15.0, "predictions": {"probabilities": [-12.710494041442871, -10.07193660736084], "logits": [NaN, NaN]}, "groundTruth": [0.0, 0.0]}, {"startTime": 15.0, "endTime": 20.0, "predictions": {"probabilities": [-15.478059768676758, -19.95088005065918], "logits": [NaN, NaN]}, "groundTruth": [0.0, 0.0]}]]}