{"modelName": "devise-221108-v4-ep149", "version": "1", "fileId": "27eba54852b04aeab81707af189b023b", "classIds": ["Crex crex", "Scolopax rusticola"], "channels": [[{"startTime": 0.0, "endTime": 2.0, "predictions": {"probabilities": [7.569455468464597e-21, 5.360400336940074e-07], "logits": []}, "groundTruth": [0.0, 0.0]}, {"startTime": 5.0, "endTime": 7.0, "predictions": {"probabilities": [4.429486005772459e-18, 5.943258656770922e-06], "logits": []}, "groundTruth": [0.0, 0.0]}, {"startTime": 10.0, "endTime": 12.0, "predictions": {"probabilities": [4.728581101760847e-26, 8.866504863647151e-09], "logits": []}, "groundTruth": [0.0, 0.0]}, {"startTime": 15.0, "endTime": 17.0, "predictions": {"probabilities": [2.6080197488209868e-23, 2.3784895120115834e-07], "logits": []}, "groundTruth": [0.0, 0.0]}, {"startTime": 18.0, "endTime": 20.0, "predictions": {"probabilities": [1.9553552650425562e-27, 1.5251490737000495e-08], "logits": []}, "groundTruth": [0.0, 0.0]}]]}