{"modelName": "devise-221108-v4-ep149", "version": "1", "fileId": "41d5f0d4cac049b6b78e13d59686f86e", "classIds": ["Crex crex", "Scolopax rusticola"], "channels": [[{"startTime": 0.0, "endTime": 2.0, "predictions": {"probabilities": [2.020003126680945e-21, 0.00032555157667957246], "logits": []}, "groundTruth": [0.0, 0.0]}, {"startTime": 5.0, "endTime": 7.0, "predictions": {"probabilities": [1.247037556432182e-17, 0.001138240215368569], "logits": []}, "groundTruth": [0.0, 0.0]}, {"startTime": 10.0, "endTime": 12.0, "predictions": {"probabilities": [1.266579483336788e-16, 0.003506581299006939], "logits": []}, "groundTruth": [0.0, 0.0]}, {"startTime": 15.0, "endTime": 17.0, "predictions": {"probabilities": [4.206878443692441e-13, 0.012769006192684174], "logits": []}, "groundTruth": [0.0, 0.0]}, {"startTime": 18.0, "endTime": 20.0, "predictions": {"probabilities": [3.1411005591811154e-15, 0.0036279591731727123], "logits": []}, "groundTruth": [0.0, 0.0]}]]}