{"modelName": "devise-221108-v4-ep149", "version": "1", "fileId": "7f7013209dcb4cb182b186ce3b1d70d3", "classIds": ["Crex crex", "Scolopax rusticola"], "channels": [[{"startTime": 0.0, "endTime": 2.0, "predictions": {"probabilities": [3.896195774105566e-30, 9.896051755831081e-10], "logits": []}, "groundTruth": [0.0, 0.0]}, {"startTime": 5.0, "endTime": 7.0, "predictions": {"probabilities": [1.3920659687158982e-20, 4.650875780498609e-05], "logits": []}, "groundTruth": [0.0, 0.0]}, {"startTime": 10.0, "endTime": 12.0, "predictions": {"probabilities": [1.5740488740673146e-23, 2.1404106519185007e-05], "logits": []}, "groundTruth": [0.0, 0.0]}, {"startTime": 15.0, "endTime": 17.0, "predictions": {"probabilities": [1.76279329430182e-20, 3.5843424939230317e-06], "logits": []}, "groundTruth": [0.0, 0.0]}, {"startTime": 18.0, "endTime": 20.0, "predictions": {"probabilities": [1.8238187688826487e-16, 0.02591956965625286], "logits": []}, "groundTruth": [0.0, 0.0]}]]}