{"modelName": "devise-221108-v4-ep149", "version": "1", "fileId": "c137fc0342b6407b9312a76c67a64836", "classIds": ["Crex crex", "Scolopax rusticola"], "channels": [[{"startTime": 0.0, "endTime": 2.0, "predictions": {"probabilities": [1.255610741247859e-13, 0.006641634739935398], "logits": []}, "groundTruth": [0.0, 0.0]}, {"startTime": 5.0, "endTime": 7.0, "predictions": {"probabilities": [5.681405218995941e-21, 0.2764330804347992], "logits": []}, "groundTruth": [0.0, 0.0]}, {"startTime": 10.0, "endTime": 12.0, "predictions": {"probabilities": [1.5282107447989884e-14, 0.002558579668402672], "logits": []}, "groundTruth": [0.0, 0.0]}, {"startTime": 15.0, "endTime": 17.0, "predictions": {"probabilities": [3.1472010598738304e-14, 0.0024004015140235424], "logits": []}, "groundTruth": [0.0, 0.0]}, {"startTime": 18.0, "endTime": 20.0, "predictions": {"probabilities": [1.37669877667973e-12, 0.0021304707042872906], "logits": []}, "groundTruth": [0.0, 0.0]}]]}