{"modelName": "devise-221108-v4-ep149", "version": "1", "fileId": "de9686267f49462b9a9c9327858cea2d", "classIds": ["Crex crex", "Scolopax rusticola"], "channels": [[{"startTime": 0.0, "endTime": 2.0, "predictions": {"probabilities": [2.0714137992339865e-19, 3.0373671506822575e-06], "logits": []}, "groundTruth": [0.0, 0.0]}, {"startTime": 5.0, "endTime": 7.0, "predictions": {"probabilities": [6.305738761068109e-17, 0.00016796443378552794], "logits": []}, "groundTruth": [0.0, 0.0]}, {"startTime": 10.0, "endTime": 12.0, "predictions": {"probabilities": [3.110648438370998e-21, 4.829850240639644e-06], "logits": []}, "groundTruth": [0.0, 0.0]}, {"startTime": 15.0, "endTime": 17.0, "predictions": {"probabilities": [3.2490559900799715e-21, 1.2107740303690662e-06], "logits": []}, "groundTruth": [0.0, 0.0]}, {"startTime": 18.0, "endTime": 20.0, "predictions": {"probabilities": [1.6143089330510846e-18, 1.1662421457003802e-05], "logits": []}, "groundTruth": [0.0, 0.0]}]]}