{"modelName": "devise-221108-v4-ep149", "version": "1", "fileId": "e014693bab1342e1891b49432fed30bc", "classIds": ["Crex crex", "Scolopax rusticola"], "channels": [[{"startTime": 0.0, "endTime": 2.0, "predictions": {"probabilities": [4.872344278226814e-17, 0.0036428633611649275], "logits": []}, "groundTruth": [0.0, 0.0]}, {"startTime": 5.0, "endTime": 7.0, "predictions": {"probabilities": [6.386668126966827e-17, 0.01109920721501112], "logits": []}, "groundTruth": [0.0, 0.0]}, {"startTime": 10.0, "endTime": 12.0, "predictions": {"probabilities": [2.3085626834652706e-13, 0.008321387693285942], "logits": []}, "groundTruth": [0.0, 0.0]}, {"startTime": 15.0, "endTime": 17.0, "predictions": {"probabilities": [2.3344369904347182e-15, 0.002884525340050459], "logits": []}, "groundTruth": [0.0, 0.0]}, {"startTime": 18.0, "endTime": 20.0, "predictions": {"probabilities": [3.9149421009708474e-13, 0.009108135476708412], "logits": []}, "groundTruth": [0.0, 0.0]}]]}