{"modelName": "devise-221108-v4-ep149", "version": "1", "fileId": "f64bf0a59c204d32ac2311be650f919b", "classIds": ["Crex crex", "Scolopax rusticola"], "channels": [[{"startTime": 0.0, "endTime": 2.0, "predictions": {"probabilities": [3.1793830420672473e-18, 0.0009799344697967172], "logits": []}, "groundTruth": [0.0, 0.0]}, {"startTime": 5.0, "endTime": 7.0, "predictions": {"probabilities": [1.2844770946401513e-21, 3.4677581425057724e-05], "logits": []}, "groundTruth": [0.0, 0.0]}, {"startTime": 10.0, "endTime": 12.0, "predictions": {"probabilities": [7.966868092975877e-21, 0.00024817069061100483], "logits": []}, "groundTruth": [0.0, 0.0]}, {"startTime": 15.0, "endTime": 17.0, "predictions": {"probabilities": [8.447845043478032e-22, 0.00038166396552696824], "logits": []}, "groundTruth": [0.0, 0.0]}, {"startTime": 20.0, "endTime": 22.0, "predictions": {"probabilities": [1.760695535187817e-21, 0.00029052264289930463], "logits": []}, "groundTruth": [0.0, 0.0]}, {"startTime": 25.0, "endTime": 27.0, "predictions": {"probabilities": [8.853945790724407e-21, 0.00027419233811087906], "logits": []}, "groundTruth": [0.0, 0.0]}, {"startTime": 30.0, "endTime": 32.0, "predictions": {"probabilities": [3.8573509608401866e-20, 0.00024952474632300436], "logits": []}, "groundTruth": [0.0, 0.0]}, {"startTime": 35.0, "endTime": 37.0, "predictions": {"probabilities": [1.3964073292256548e-18, 2.537825275794603e-05], "logits": []}, "groundTruth": [0.0, 0.0]}, {"startTime": 40.0, "endTime": 42.0, "predictions": {"probabilities": [4.4147378924385213e-20, 2.9134796477592317e-06], "logits": []}, "groundTruth": [0.0, 0.0]}, {"startTime": 44.0, "endTime": 46.0, "predictions": {"probabilities": [5.828428293782042e-25, 0.20803403854370117], "logits": []}, "groundTruth": [0.0, 0.0]}]]}