{"modelName": "devise-221117-v1-ep150", "version": "1", "fileId": "02fdc38ef37e4514a90d1d80ca62914b", "classIds": ["Crex crex", "Scolopax rusticola"], "channels": [[{"startTime": 0.0, "endTime": 5.0, "predictions": {"probabilities": [2.5006764190038666e-05, 0.033691953867673874], "logits": []}, "groundTruth": [0.0, 0.0]}, {"startTime": 5.0, "endTime": 10.0, "predictions": {"probabilities": [0.0004919117200188339, 0.5033547282218933], "logits": []}, "groundTruth": [0.0, 0.0]}, {"startTime": 10.0, "endTime": 15.0, "predictions": {"probabilities": [0.00012059327855240554, 0.16950851678848267], "logits": []}, "groundTruth": [0.0, 0.0]}, {"startTime": 15.0, "endTime": 20.0, "predictions": {"probabilities": [6.245661643333733e-05, 0.06900016963481903], "logits": []}, "groundTruth": [0.0, 0.0]}]]}