{"modelName": "devise-221117-v1-ep150", "version": "1", "fileId": "24d40c110e5640bc9c96dcca3c26bcb8", "classIds": ["Crex crex", "Scolopax rusticola"], "channels": [[{"startTime": 0.0, "endTime": 5.0, "predictions": {"probabilities": [3.291433313279413e-05, 0.23867440223693848], "logits": []}, "groundTruth": [0.0, 0.0]}, {"startTime": 5.0, "endTime": 10.0, "predictions": {"probabilities": [6.075079727452248e-05, 0.18776215612888336], "logits": []}, "groundTruth": [0.0, 0.0]}, {"startTime": 10.0, "endTime": 15.0, "predictions": {"probabilities": [3.1604940886609256e-05, 0.109235018491745], "logits": []}, "groundTruth": [0.0, 0.0]}, {"startTime": 15.0, "endTime": 20.0, "predictions": {"probabilities": [4.606813035934465e-06, 0.005023112986236811], "logits": []}, "groundTruth": [0.0, 0.0]}]]}