{"modelName": "devise-221117-v1-ep150", "version": "1", "fileId": "2a0b425cf06a4c55ac69b588aaa45e3e", "classIds": ["Crex crex", "Scolopax rusticola"], "channels": [[{"startTime": 0.0, "endTime": 5.0, "predictions": {"probabilities": [-8.199396133422852, 2.2760391235351562], "logits": [NaN, NaN]}, "groundTruth": [0.0, 0.0]}, {"startTime": 5.0, "endTime": 10.0, "predictions": {"probabilities": [-13.466681480407715, 11.709366798400879], "logits": [NaN, NaN]}, "groundTruth": [0.0, 1.0]}, {"startTime": 10.0, "endTime": 15.0, "predictions": {"probabilities": [-12.252732276916504, 8.342839241027832], "logits": [NaN, NaN]}, "groundTruth": [0.0, 1.0]}, {"startTime": 15.0, "endTime": 20.0, "predictions": {"probabilities": [-11.813642501831055, 7.9856858253479], "logits": [NaN, NaN]}, "groundTruth": [0.0, 1.0]}, {"startTime": 20.0, "endTime": 25.0, "predictions": {"probabilities": [-17.029972076416016, 16.38652801513672], "logits": [NaN, NaN]}, "groundTruth": [0.0, 1.0]}]]}