{"modelName": "devise-221117-v1-ep150", "version": "1", "fileId": "58c00a43cdfb4a799784dd559d3aa791", "classIds": ["Crex crex", "Scolopax rusticola"], "channels": [[{"startTime": 0.0, "endTime": 5.0, "predictions": {"probabilities": [-11.226800918579102, -3.3570785522460938], "logits": [NaN, NaN]}, "groundTruth": [0.0, 0.0]}, {"startTime": 5.0, "endTime": 10.0, "predictions": {"probabilities": [-8.265871047973633, -0.47829315066337585], "logits": [NaN, NaN]}, "groundTruth": [0.0, 0.0]}, {"startTime": 10.0, "endTime": 15.0, "predictions": {"probabilities": [-7.798323631286621, 0.6630511283874512], "logits": [NaN, 0.6769208908081055]}, "groundTruth": [0.0, 0.0]}, {"startTime": 15.0, "endTime": 20.0, "predictions": {"probabilities": [-8.24720287322998, -0.6840885877609253], "logits": [NaN, NaN]}, "groundTruth": [0.0, 0.0]}]]}