{"modelName": "devise-221117-v1-ep150", "version": "1", "fileId": "69e72fa556eb47478572b4525c1129f5", "classIds": ["Crex crex", "Scolopax rusticola"], "channels": [[{"startTime": 0.0, "endTime": 5.0, "predictions": {"probabilities": [-18.930221557617188, 21.600936889648438], "logits": [NaN, NaN]}, "groundTruth": [0.0, 1.0]}, {"startTime": 5.0, "endTime": 10.0, "predictions": {"probabilities": [-13.746776580810547, 7.294534683227539], "logits": [NaN, NaN]}, "groundTruth": [0.0, 1.0]}, {"startTime": 10.0, "endTime": 15.0, "predictions": {"probabilities": [-14.113070487976074, 11.636479377746582], "logits": [NaN, NaN]}, "groundTruth": [0.0, 1.0]}, {"startTime": 15.0, "endTime": 20.0, "predictions": {"probabilities": [-15.530821800231934, 7.303750991821289], "logits": [NaN, NaN]}, "groundTruth": [0.0, 1.0]}, {"startTime": 16.0, "endTime": 21.0, "predictions": {"probabilities": [-18.878854751586914, 13.398527145385742], "logits": [NaN, NaN]}, "groundTruth": [0.0, 1.0]}]]}