{"modelName": "devise-221117-v1-ep150", "version": "1", "fileId": "798f6460b4954394bbd9d6a58fec74a8", "classIds": ["Crex crex", "Scolopax rusticola"], "channels": [[{"startTime": 0.0, "endTime": 5.0, "predictions": {"probabilities": [-10.223237037658691, -3.1165735721588135], "logits": [NaN, NaN]}, "groundTruth": [0.0, 1.0]}, {"startTime": 5.0, "endTime": 10.0, "predictions": {"probabilities": [-13.594965934753418, 1.2923177480697632], "logits": [NaN, NaN]}, "groundTruth": [0.0, 1.0]}, {"startTime": 10.0, "endTime": 15.0, "predictions": {"probabilities": [-15.009218215942383, 6.227799892425537], "logits": [NaN, NaN]}, "groundTruth": [0.0, 1.0]}, {"startTime": 11.0, "endTime": 16.0, "predictions": {"probabilities": [-14.413302421569824, 1.1441621780395508], "logits": [NaN, NaN]}, "groundTruth": [0.0, 0.0]}]]}