{"modelName": "devise-221117-v1-ep150", "version": "1", "fileId": "8dbaa23932a54e3e8d24ca483cb3f170", "classIds": ["Crex crex", "Scolopax rusticola"], "channels": [[{"startTime": 0.0, "endTime": 5.0, "predictions": {"probabilities": [-12.087814331054688, -4.713670253753662], "logits": [NaN, NaN]}, "groundTruth": [0.0, 0.0]}, {"startTime": 5.0, "endTime": 10.0, "predictions": {"probabilities": [-10.461570739746094, -2.4975333213806152], "logits": [NaN, NaN]}, "groundTruth": [0.0, 0.0]}, {"startTime": 10.0, "endTime": 15.0, "predictions": {"probabilities": [-8.904088973999023, -1.9258513450622559], "logits": [NaN, NaN]}, "groundTruth": [0.0, 0.0]}, {"startTime": 15.0, "endTime": 20.0, "predictions": {"probabilities": [-14.019668579101562, -7.2266459465026855], "logits": [NaN, NaN]}, "groundTruth": [0.0, 0.0]}]]}