{"modelName": "devise-221117-v1-ep150", "version": "1", "fileId": "b90f841a31e44abcbb77aaebeb622d88", "classIds": ["Crex crex", "Scolopax rusticola"], "channels": [[{"startTime": 0.0, "endTime": 5.0, "predictions": {"probabilities": [5.103332568978658e-06, 0.005019289907068014], "logits": []}, "groundTruth": [0.0, 0.0]}, {"startTime": 5.0, "endTime": 10.0, "predictions": {"probabilities": [0.00015101615281309932, 0.611112654209137], "logits": []}, "groundTruth": [0.0, 0.0]}, {"startTime": 10.0, "endTime": 15.0, "predictions": {"probabilities": [2.479448539816076e-07, 0.9999421834945679], "logits": []}, "groundTruth": [0.0, 0.0]}, {"startTime": 15.0, "endTime": 20.0, "predictions": {"probabilities": [1.4502550982342655e-07, 0.9999901056289673], "logits": []}, "groundTruth": [0.0, 0.0]}]]}