{"modelName": "devise-221117-v1-ep150", "version": "1", "fileId": "d1edc84476fd4186b8f065c9fee04695", "classIds": ["Crex crex", "Scolopax rusticola"], "channels": [[{"startTime": 0.0, "endTime": 5.0, "predictions": {"probabilities": [-7.98873233795166, 0.0740109458565712], "logits": [NaN, -2.5266494750976562]}, "groundTruth": [0.0, 0.0]}, {"startTime": 5.0, "endTime": 10.0, "predictions": {"probabilities": [-7.631274700164795, 0.20824941992759705], "logits": [NaN, -1.3355098962783813]}, "groundTruth": [0.0, 0.0]}, {"startTime": 10.0, "endTime": 15.0, "predictions": {"probabilities": [-10.964548110961914, 2.996649980545044], "logits": [NaN, NaN]}, "groundTruth": [0.0, 0.0]}, {"startTime": 15.0, "endTime": 20.0, "predictions": {"probabilities": [-9.780258178710938, -2.8895699977874756], "logits": [NaN, NaN]}, "groundTruth": [0.0, 0.0]}]]}