{"modelName": "devise-221117-v1-ep150", "version": "1", "fileId": "e76dba92e1a746df98103c542199f6ad", "classIds": ["Crex crex", "Scolopax rusticola"], "channels": [[{"startTime": 0.0, "endTime": 5.0, "predictions": {"probabilities": [-9.021896362304688, -0.6476914882659912], "logits": [NaN, NaN]}, "groundTruth": [0.0, 0.0]}, {"startTime": 5.0, "endTime": 10.0, "predictions": {"probabilities": [-11.068140983581543, 4.576807498931885], "logits": [NaN, NaN]}, "groundTruth": [0.0, 0.0]}, {"startTime": 10.0, "endTime": 15.0, "predictions": {"probabilities": [-9.156355857849121, 3.47890567779541], "logits": [NaN, NaN]}, "groundTruth": [0.0, 0.0]}, {"startTime": 15.0, "endTime": 20.0, "predictions": {"probabilities": [-10.764307022094727, -2.764047622680664], "logits": [NaN, NaN]}, "groundTruth": [0.0, 0.0]}]]}