{"modelName": "devise-221108-v8-ep423", "version": "1", "fileId": "01e6d70f2cb64406a4af07323c9504b0", "classIds": ["Crex crex", "Scolopax rusticola"], "channels": [[{"startTime": 0.0, "endTime": 5.0, "predictions": {"probabilities": [-22.36785125732422, -5.454148769378662], "logits": [NaN, NaN]}, "groundTruth": [0.0, 0.0]}, {"startTime": 5.0, "endTime": 10.0, "predictions": {"probabilities": [-23.328365325927734, 5.653966426849365], "logits": [NaN, NaN]}, "groundTruth": [0.0, 0.0]}, {"startTime": 10.0, "endTime": 15.0, "predictions": {"probabilities": [-18.070894241333008, -3.584038734436035], "logits": [NaN, NaN]}, "groundTruth": [0.0, 0.0]}, {"startTime": 15.0, "endTime": 20.0, "predictions": {"probabilities": [-34.91698455810547, 18.23689079284668], "logits": [NaN, NaN]}, "groundTruth": [0.0, 0.0]}]]}