{"modelName": "devise-221108-v8-ep423", "version": "1", "fileId": "28d7b04ebc444dba91dd56d8415724fa", "classIds": ["Crex crex", "Scolopax rusticola"], "channels": [[{"startTime": 0.0, "endTime": 5.0, "predictions": {"probabilities": [-14.080316543579102, -0.2153835892677307], "logits": [NaN, NaN]}, "groundTruth": [0.0, 1.0]}, {"startTime": 5.0, "endTime": 10.0, "predictions": {"probabilities": [-33.29562759399414, 18.792104721069336], "logits": [NaN, NaN]}, "groundTruth": [0.0, 1.0]}, {"startTime": 10.0, "endTime": 15.0, "predictions": {"probabilities": [-25.875858306884766, 11.335232734680176], "logits": [NaN, NaN]}, "groundTruth": [0.0, 1.0]}, {"startTime": 15.0, "endTime": 20.0, "predictions": {"probabilities": [-36.70706558227539, 26.657665252685547], "logits": [NaN, NaN]}, "groundTruth": [0.0, 1.0]}, {"startTime": 20.0, "endTime": 25.0, "predictions": {"probabilities": [-17.454952239990234, 6.968770980834961], "logits": [NaN, NaN]}, "groundTruth": [0.0, 1.0]}, {"startTime": 25.0, "endTime": 30.0, "predictions": {"probabilities": [-12.570487022399902, -0.8644721508026123], "logits": [NaN, NaN]}, "groundTruth": [0.0, 1.0]}, {"startTime": 26.0, "endTime": 31.0, "predictions": {"probabilities": [-13.826692581176758, -1.3172547817230225], "logits": [NaN, NaN]}, "groundTruth": [0.0, 1.0]}]]}