{"modelName": "devise-221108-v8-ep423", "version": "1", "fileId": "433a857763c045668c835c2c4986f004", "classIds": ["Crex crex", "Scolopax rusticola"], "channels": [[{"startTime": 0.0, "endTime": 5.0, "predictions": {"probabilities": [8.939655682382863e-10, 0.006512369494885206], "logits": []}, "groundTruth": [0.0, 0.0]}, {"startTime": 5.0, "endTime": 10.0, "predictions": {"probabilities": [1.816022887624058e-08, 0.021060947328805923], "logits": []}, "groundTruth": [0.0, 0.0]}, {"startTime": 10.0, "endTime": 15.0, "predictions": {"probabilities": [2.4284041444389004e-10, 0.10540267080068588], "logits": []}, "groundTruth": [0.0, 0.0]}, {"startTime": 15.0, "endTime": 20.0, "predictions": {"probabilities": [2.2365771457089068e-08, 0.02552555687725544], "logits": []}, "groundTruth": [0.0, 0.0]}]]}