{"modelName": "devise-221108-v8-ep423", "version": "1", "fileId": "52ca77df6b3b4c87a527bc233ef06516", "classIds": ["Crex crex", "Scolopax rusticola"], "channels": [[{"startTime": 0.0, "endTime": 5.0, "predictions": {"probabilities": [9.233023789967376e-10, 0.04027188569307327], "logits": []}, "groundTruth": [0.0, 0.0]}, {"startTime": 5.0, "endTime": 10.0, "predictions": {"probabilities": [6.423478193795518e-09, 0.18039393424987793], "logits": []}, "groundTruth": [0.0, 0.0]}, {"startTime": 10.0, "endTime": 15.0, "predictions": {"probabilities": [1.1290613999292987e-09, 0.03654913604259491], "logits": []}, "groundTruth": [0.0, 0.0]}, {"startTime": 15.0, "endTime": 20.0, "predictions": {"probabilities": [1.4645403778601462e-09, 0.01985780894756317], "logits": []}, "groundTruth": [0.0, 0.0]}]]}