{"modelName": "devise-221108-v8-ep423", "version": "1", "fileId": "927ccf2f54be4beda36996a73cae8b51", "classIds": ["Crex crex", "Scolopax rusticola"], "channels": [[{"startTime": 0.0, "endTime": 5.0, "predictions": {"probabilities": [-32.192047119140625, 14.467611312866211], "logits": [NaN, NaN]}, "groundTruth": [0.0, 0.0]}, {"startTime": 5.0, "endTime": 10.0, "predictions": {"probabilities": [-36.01995086669922, 25.116134643554688], "logits": [NaN, NaN]}, "groundTruth": [0.0, 1.0]}, {"startTime": 10.0, "endTime": 15.0, "predictions": {"probabilities": [-39.403968811035156, 29.829750061035156], "logits": [NaN, NaN]}, "groundTruth": [0.0, 1.0]}, {"startTime": 15.0, "endTime": 20.0, "predictions": {"probabilities": [-31.30288314819336, 19.04245376586914], "logits": [NaN, NaN]}, "groundTruth": [0.0, 1.0]}, {"startTime": 20.0, "endTime": 25.0, "predictions": {"probabilities": [-30.143312454223633, 19.217754364013672], "logits": [NaN, NaN]}, "groundTruth": [0.0, 1.0]}, {"startTime": 25.0, "endTime": 30.0, "predictions": {"probabilities": [-18.902721405029297, -0.35434800386428833], "logits": [NaN, NaN]}, "groundTruth": [0.0, 1.0]}, {"startTime": 30.0, "endTime": 35.0, "predictions": {"probabilities": [-20.034502029418945, 1.9660959243774414], "logits": [NaN, NaN]}, "groundTruth": [0.0, 1.0]}, {"startTime": 31.0, "endTime": 36.0, "predictions": {"probabilities": [-17.076433181762695, -3.3681371212005615], "logits": [NaN, NaN]}, "groundTruth": [0.0, 1.0]}]]}