{"modelName": "devise-221108-v8-ep423", "version": "1", "fileId": "9e9b368205e5494ba86bb3fdf1370964", "classIds": ["Crex crex", "Scolopax rusticola"], "channels": [[{"startTime": 0.0, "endTime": 5.0, "predictions": {"probabilities": [-18.283058166503906, -3.752819776535034], "logits": [NaN, NaN]}, "groundTruth": [0.0, 0.0]}, {"startTime": 5.0, "endTime": 10.0, "predictions": {"probabilities": [-16.501432418823242, -2.698618173599243], "logits": [NaN, NaN]}, "groundTruth": [0.0, 0.0]}, {"startTime": 10.0, "endTime": 15.0, "predictions": {"probabilities": [-18.476036071777344, -0.822860836982727], "logits": [NaN, NaN]}, "groundTruth": [0.0, 0.0]}, {"startTime": 15.0, "endTime": 20.0, "predictions": {"probabilities": [-18.493833541870117, -1.8955813646316528], "logits": [NaN, NaN]}, "groundTruth": [0.0, 0.0]}]]}