{"modelName": "devise-221108-v8-ep423", "version": "1", "fileId": "b214d02980c6438db9a17cfcbec47196", "classIds": ["Crex crex", "Scolopax rusticola"], "channels": [[{"startTime": 0.0, "endTime": 5.0, "predictions": {"probabilities": [-18.832717895507812, -1.0701476335525513], "logits": [NaN, NaN]}, "groundTruth": [0.0, 0.0]}, {"startTime": 5.0, "endTime": 10.0, "predictions": {"probabilities": [-22.621301651000977, -2.682522773742676], "logits": [NaN, NaN]}, "groundTruth": [0.0, 0.0]}, {"startTime": 10.0, "endTime": 15.0, "predictions": {"probabilities": [-20.499107360839844, -4.704616069793701], "logits": [NaN, NaN]}, "groundTruth": [0.0, 0.0]}, {"startTime": 15.0, "endTime": 20.0, "predictions": {"probabilities": [-18.379179000854492, -1.996958613395691], "logits": [NaN, NaN]}, "groundTruth": [0.0, 0.0]}]]}