{"modelName": "devise-221108-v8-ep423", "version": "1", "fileId": "ca34dd6bd5ab4b2e97c54c756a008194", "classIds": ["Crex crex", "Scolopax rusticola"], "channels": [[{"startTime": 0.0, "endTime": 5.0, "predictions": {"probabilities": [4.955317489674371e-09, 0.2088308185338974], "logits": []}, "groundTruth": [0.0, 1.0]}, {"startTime": 5.0, "endTime": 10.0, "predictions": {"probabilities": [2.4565755415387625e-17, 1.0], "logits": []}, "groundTruth": [0.0, 1.0]}, {"startTime": 10.0, "endTime": 15.0, "predictions": {"probabilities": [2.210159342325678e-14, 1.0], "logits": []}, "groundTruth": [0.0, 1.0]}, {"startTime": 15.0, "endTime": 20.0, "predictions": {"probabilities": [5.234159417000228e-08, 0.6106826663017273], "logits": []}, "groundTruth": [0.0, 1.0]}, {"startTime": 16.0, "endTime": 21.0, "predictions": {"probabilities": [1.2705775986887602e-07, 0.1518765687942505], "logits": []}, "groundTruth": [0.0, 0.0]}]]}