{"modelName": "devise-221108-v8-ep423", "version": "1", "fileId": "d018d6023b4848f38e98d7179440450e", "classIds": ["Crex crex", "Scolopax rusticola"], "channels": [[{"startTime": 0.0, "endTime": 5.0, "predictions": {"probabilities": [-15.212262153625488, 2.8293702602386475], "logits": [NaN, NaN]}, "groundTruth": [0.0, 0.0]}, {"startTime": 5.0, "endTime": 10.0, "predictions": {"probabilities": [-18.684572219848633, 4.840997695922852], "logits": [NaN, NaN]}, "groundTruth": [0.0, 1.0]}, {"startTime": 10.0, "endTime": 15.0, "predictions": {"probabilities": [-29.591873168945312, 19.929901123046875], "logits": [NaN, NaN]}, "groundTruth": [0.0, 1.0]}, {"startTime": 15.0, "endTime": 20.0, "predictions": {"probabilities": [-19.476150512695312, 6.481757164001465], "logits": [NaN, NaN]}, "groundTruth": [0.0, 1.0]}, {"startTime": 20.0, "endTime": 25.0, "predictions": {"probabilities": [-29.232616424560547, 13.015740394592285], "logits": [NaN, NaN]}, "groundTruth": [0.0, 1.0]}, {"startTime": 25.0, "endTime": 30.0, "predictions": {"probabilities": [-21.027576446533203, 7.35953426361084], "logits": [NaN, NaN]}, "groundTruth": [0.0, 1.0]}, {"startTime": 26.0, "endTime": 31.0, "predictions": {"probabilities": [-16.384361267089844, -0.16009369492530823], "logits": [NaN, NaN]}, "groundTruth": [0.0, 1.0]}]]}