{"modelName": "devise-221108-v8-ep423", "version": "1", "fileId": "dfe6d6e8e8cb42d8a5f9579a3e075a23", "classIds": ["Crex crex", "Scolopax rusticola"], "channels": [[{"startTime": 0.0, "endTime": 5.0, "predictions": {"probabilities": [2.8258968498562353e-08, 0.05418789014220238], "logits": []}, "groundTruth": [0.0, 0.0]}, {"startTime": 5.0, "endTime": 10.0, "predictions": {"probabilities": [1.3216124727932765e-07, 0.07211048156023026], "logits": []}, "groundTruth": [0.0, 0.0]}, {"startTime": 10.0, "endTime": 15.0, "predictions": {"probabilities": [5.086657139941053e-08, 0.03430962190032005], "logits": []}, "groundTruth": [0.0, 0.0]}, {"startTime": 15.0, "endTime": 20.0, "predictions": {"probabilities": [6.040394140427452e-08, 0.03745713084936142], "logits": []}, "groundTruth": [0.0, 0.0]}]]}